{"version":3,"kind":"Notebook","sha256":"7d66f7fcca7c235dda52ad3202d4cd533be0a1feef1ee5d251f31a67b4d30bf0","slug":"zweiteseite","location":"/zweiteseite.ipynb","dependencies":[],"frontmatter":{"title":"🏁 Beispiel 4: Fazit & Nächste Schritte (Projekt-Abschluss)","content_includes_title":true,"kernelspec":{"name":"python3","display_name":"Python 3","language":"python"},"authors":[{"nameParsed":{"literal":"Max Mustermann","given":"Max","family":"Mustermann"},"name":"Max Mustermann","corresponding":true,"email":"max.mustermann@example.com","id":"contributors-Users\\MohamadTayara\\PycharmProjects\\myjbook\\book1\\myst-generated-uid-0"}],"github":"https://github.com/dein-benutzername/dein-projekt-repo","keywords":["python","data science","jupyter book","pandas","numpy"],"exports":[{"format":"ipynb","filename":"zweiteseite.ipynb","url":"/zweiteseite-dae4155dcff23125f88f9b71a1f4f633.ipynb"}]},"widgets":{},"mdast":{"type":"root","children":[{"type":"block","kind":"notebook-content","children":[{"type":"heading","depth":1,"position":{"start":{"line":1,"column":1},"end":{"line":1,"column":1}},"children":[{"type":"text","value":"🏁 Beispiel 4: Fazit & Nächste Schritte (Projekt-Abschluss)","position":{"start":{"line":1,"column":1},"end":{"line":1,"column":1}},"key":"o3A9syf1Yl"}],"identifier":"id-beispiel-4-fazit-n-chste-schritte-projekt-abschluss","label":"🏁 Beispiel 4: Fazit & Nächste Schritte (Projekt-Abschluss)","html_id":"id-beispiel-4-fazit-n-chste-schritte-projekt-abschluss","implicit":true,"key":"uBToTCsGaN"},{"type":"paragraph","position":{"start":{"line":2,"column":1},"end":{"line":2,"column":1}},"children":[{"type":"text","value":"Ideal für das Ende deines Notebooks, um die Ergebnisse zusammenzufassen.","position":{"start":{"line":2,"column":1},"end":{"line":2,"column":1}},"key":"Kd11JcypF3"}],"key":"j9CBbPxPiP"}],"key":"euIOQlWUbh"},{"type":"block","kind":"notebook-content","children":[{"type":"heading","depth":1,"position":{"start":{"line":1,"column":1},"end":{"line":1,"column":1}},"children":[{"type":"text","value":"📌 Fazit und Ausblick","position":{"start":{"line":1,"column":1},"end":{"line":1,"column":1}},"key":"n7SKRPsIPz"}],"identifier":"id-fazit-und-ausblick","label":"📌 Fazit und Ausblick","html_id":"id-fazit-und-ausblick","implicit":true,"key":"GzteDEzaO7"},{"type":"paragraph","position":{"start":{"line":3,"column":1},"end":{"line":3,"column":1}},"children":[{"type":"text","value":"Die Analyse der Daten zeigt deutliche saisonale Abhängigkeiten. Die wichtigsten Erkenntnisse im Überblick:","position":{"start":{"line":3,"column":1},"end":{"line":3,"column":1}},"key":"DMlams08Eu"}],"key":"KmAFEUVyyH"},{"type":"list","ordered":false,"spread":false,"position":{"start":{"line":5,"column":1},"end":{"line":7,"column":1}},"children":[{"type":"listItem","spread":true,"position":{"start":{"line":5,"column":1},"end":{"line":5,"column":1}},"children":[{"type":"paragraph","children":[{"type":"strong","position":{"start":{"line":5,"column":1},"end":{"line":5,"column":1}},"children":[{"type":"text","value":"Hauptergebnis:","position":{"start":{"line":5,"column":1},"end":{"line":5,"column":1}},"key":"jyHM9ijKzu"}],"key":"X9ivUeFeIg"},{"type":"text","value":" Die Umsätze steigen im März im Vergleich zu den Vormonaten um ca. 15%.","position":{"start":{"line":5,"column":1},"end":{"line":5,"column":1}},"key":"LiaVyqS62w"}],"key":"GA35414cRU"}],"key":"KtllHx5gB1"},{"type":"listItem","spread":true,"position":{"start":{"line":6,"column":1},"end":{"line":7,"column":1}},"children":[{"type":"paragraph","children":[{"type":"strong","position":{"start":{"line":6,"column":1},"end":{"line":6,"column":1}},"children":[{"type":"text","value":"Auffälligkeit:","position":{"start":{"line":6,"column":1},"end":{"line":6,"column":1}},"key":"ZsXUxQyvXk"}],"key":"N5lawGsfPE"},{"type":"text","value":" Stornierungen treten gehäuft an Wochenenden auf. Hier sollten wir die Support-Zeiten prüfen.","position":{"start":{"line":6,"column":1},"end":{"line":6,"column":1}},"key":"TqeqYvdCaz"}],"key":"RGD22UQxUp"}],"key":"P6evzmkInQ"}],"key":"Ea5ThGV9Vk"},{"type":"thematicBreak","position":{"start":{"line":8,"column":1},"end":{"line":8,"column":1}},"key":"KD8YAYHd8D"},{"type":"heading","depth":2,"position":{"start":{"line":10,"column":1},"end":{"line":10,"column":1}},"children":[{"type":"text","value":"🗺️ Nächste Schritte (Roadmap)","position":{"start":{"line":10,"column":1},"end":{"line":10,"column":1}},"key":"HuAe514xJ1"}],"identifier":"id-n-chste-schritte-roadmap","label":"🗺️ Nächste Schritte (Roadmap)","html_id":"id-n-chste-schritte-roadmap","implicit":true,"key":"iTnUlPXW5G"},{"type":"paragraph","position":{"start":{"line":12,"column":1},"end":{"line":12,"column":1}},"children":[{"type":"text","value":"Hier ist der Plan für die Weiterentwicklung des Modells:","position":{"start":{"line":12,"column":1},"end":{"line":12,"column":1}},"key":"hntMbGsVbA"}],"key":"gGy9TGsAsh"},{"type":"list","ordered":false,"spread":false,"position":{"start":{"line":14,"column":1},"end":{"line":17,"column":1}},"children":[{"type":"listItem","spread":true,"position":{"start":{"line":14,"column":1},"end":{"line":14,"column":1}},"children":[{"type":"paragraph","children":[{"type":"text","value":"Bereinigung der Ausreißer und ","position":{"start":{"line":14,"column":1},"end":{"line":14,"column":1}},"key":"vzKVFU0BS2"},{"type":"inlineCode","value":"NaN","position":{"start":{"line":14,"column":1},"end":{"line":14,"column":1}},"key":"M5SI5EIQLU"},{"type":"text","value":"-Werte.","position":{"start":{"line":14,"column":1},"end":{"line":14,"column":1}},"key":"hKLo086Xbb"}],"key":"zCmQ8BRNBd"}],"checked":true,"key":"Y5UDeDjlxX"},{"type":"listItem","spread":true,"position":{"start":{"line":15,"column":1},"end":{"line":15,"column":1}},"children":[{"type":"paragraph","children":[{"type":"text","value":"Implementierung eines einfachen Vorhersagemodells (Lineare Regression).","position":{"start":{"line":15,"column":1},"end":{"line":15,"column":1}},"key":"L7DAMR7o7r"}],"key":"AyBR2HYI0V"}],"checked":false,"key":"YPSZIAkdaJ"},{"type":"listItem","spread":true,"position":{"start":{"line":16,"column":1},"end":{"line":16,"column":1}},"children":[{"type":"paragraph","children":[{"type":"text","value":"Automatisierung des Daten-Imports über eine API-Schnittstelle.","position":{"start":{"line":16,"column":1},"end":{"line":16,"column":1}},"key":"cP8cnCLwGb"}],"key":"spMLiMttOH"}],"checked":false,"key":"Ar6VYDtQg5"},{"type":"listItem","spread":true,"position":{"start":{"line":17,"column":1},"end":{"line":17,"column":1}},"children":[{"type":"paragraph","children":[{"type":"text","value":"Export des finalen Dashboards als HTML-Bericht.","position":{"start":{"line":17,"column":1},"end":{"line":17,"column":1}},"key":"zhLNdGcXSg"}],"key":"Hn1oSOKBpN"}],"checked":false,"key":"y3CgAvj4HG"}],"key":"ioAIsGY3o3"}],"key":"T9HlzaBtsg"},{"type":"block","kind":"notebook-content","children":[{"type":"heading","depth":1,"position":{"start":{"line":1,"column":1},"end":{"line":1,"column":1}},"children":[{"type":"text","value":"📞 Beispiel 5: Projekt-Metadaten und Kontakt","position":{"start":{"line":1,"column":1},"end":{"line":1,"column":1}},"key":"ugFQY1rDjT"}],"identifier":"id-beispiel-5-projekt-metadaten-und-kontakt","label":"📞 Beispiel 5: Projekt-Metadaten und Kontakt","html_id":"id-beispiel-5-projekt-metadaten-und-kontakt","implicit":true,"key":"mUZPeAL9uH"},{"type":"paragraph","position":{"start":{"line":2,"column":1},"end":{"line":2,"column":1}},"children":[{"type":"text","value":"Damit andere sofort wissen, wer dieses Notebook erstellt hat und welche Voraussetzungen nötig sind.","position":{"start":{"line":2,"column":1},"end":{"line":2,"column":1}},"key":"qNtU80X46X"}],"key":"P4CxSqLTla"}],"key":"Z74707DFy3"},{"type":"block","kind":"notebook-content","children":[{"type":"thematicBreak","position":{"start":{"line":1,"column":1},"end":{"line":1,"column":1}},"key":"GKZ5q6vBRF"},{"type":"heading","depth":2,"position":{"start":{"line":2,"column":1},"end":{"line":2,"column":1}},"children":[{"type":"text","value":"🛠️ Projekt-Metadaten","position":{"start":{"line":2,"column":1},"end":{"line":2,"column":1}},"key":"NhIR8QWX5R"}],"identifier":"id-projekt-metadaten","label":"🛠️ Projekt-Metadaten","html_id":"id-projekt-metadaten","implicit":true,"key":"RWFOHux7R0"},{"type":"table","position":{"start":{"line":4,"column":1},"end":{"line":10,"column":1}},"children":[{"type":"tableRow","position":{"start":{"line":4,"column":1},"end":{"line":4,"column":1}},"children":[{"type":"tableCell","header":true,"align":"left","position":{"start":{"line":4,"column":1},"end":{"line":4,"column":1}},"children":[{"type":"text","value":"Info","position":{"start":{"line":4,"column":1},"end":{"line":4,"column":1}},"key":"FABC4UkNYF"}],"key":"YctxDPI8Zw"},{"type":"tableCell","header":true,"align":"left","position":{"start":{"line":4,"column":1},"end":{"line":4,"column":1}},"children":[{"type":"text","value":"Details","position":{"start":{"line":4,"column":1},"end":{"line":4,"column":1}},"key":"fYGkgH0IZa"}],"key":"GNycfNe8Yj"}],"key":"dbgNBT3tKI"},{"type":"tableRow","position":{"start":{"line":6,"column":1},"end":{"line":6,"column":1}},"children":[{"type":"tableCell","align":"left","position":{"start":{"line":6,"column":1},"end":{"line":6,"column":1}},"children":[{"type":"strong","position":{"start":{"line":6,"column":1},"end":{"line":6,"column":1}},"children":[{"type":"text","value":"Autor:","position":{"start":{"line":6,"column":1},"end":{"line":6,"column":1}},"key":"WCyYabZEXJ"}],"key":"BXRiVmwMt3"}],"key":"AMboBm4A1L"},{"type":"tableCell","align":"left","position":{"start":{"line":6,"column":1},"end":{"line":6,"column":1}},"children":[{"type":"text","value":"Dein Name / Team-Name","position":{"start":{"line":6,"column":1},"end":{"line":6,"column":1}},"key":"M8mskg4XUk"}],"key":"eeYyYJzQ4y"}],"key":"VWiFYdKYrW"},{"type":"tableRow","position":{"start":{"line":7,"column":1},"end":{"line":7,"column":1}},"children":[{"type":"tableCell","align":"left","position":{"start":{"line":7,"column":1},"end":{"line":7,"column":1}},"children":[{"type":"strong","position":{"start":{"line":7,"column":1},"end":{"line":7,"column":1}},"children":[{"type":"text","value":"Datum der Erstellung:","position":{"start":{"line":7,"column":1},"end":{"line":7,"column":1}},"key":"wBmWcKASsm"}],"key":"dvcOxYgIET"}],"key":"EUCwu4zrhC"},{"type":"tableCell","align":"left","position":{"start":{"line":7,"column":1},"end":{"line":7,"column":1}},"children":[{"type":"text","value":"18. Juni 2026","position":{"start":{"line":7,"column":1},"end":{"line":7,"column":1}},"key":"SeLSIYwpzl"}],"key":"hfRztX7kAd"}],"key":"oS0MPMJpCE"},{"type":"tableRow","position":{"start":{"line":8,"column":1},"end":{"line":8,"column":1}},"children":[{"type":"tableCell","align":"left","position":{"start":{"line":8,"column":1},"end":{"line":8,"column":1}},"children":[{"type":"strong","position":{"start":{"line":8,"column":1},"end":{"line":8,"column":1}},"children":[{"type":"text","value":"Python-Version:","position":{"start":{"line":8,"column":1},"end":{"line":8,"column":1}},"key":"KjM5TpaFb1"}],"key":"txBgngGcoo"}],"key":"feLVGtfAGU"},{"type":"tableCell","align":"left","position":{"start":{"line":8,"column":1},"end":{"line":8,"column":1}},"children":[{"type":"inlineCode","value":"3.10+","position":{"start":{"line":8,"column":1},"end":{"line":8,"column":1}},"key":"qoIHUA8mml"}],"key":"Lg3ditMUFK"}],"key":"feJqw5FpGf"},{"type":"tableRow","position":{"start":{"line":9,"column":1},"end":{"line":9,"column":1}},"children":[{"type":"tableCell","align":"left","position":{"start":{"line":9,"column":1},"end":{"line":9,"column":1}},"children":[{"type":"strong","position":{"start":{"line":9,"column":1},"end":{"line":9,"column":1}},"children":[{"type":"text","value":"Abhängigkeiten:","position":{"start":{"line":9,"column":1},"end":{"line":9,"column":1}},"key":"hSiznn8Mii"}],"key":"FEhtyN75dk"}],"key":"WcoMXgkp2O"},{"type":"tableCell","align":"left","position":{"start":{"line":9,"column":1},"end":{"line":9,"column":1}},"children":[{"type":"inlineCode","value":"pandas","position":{"start":{"line":9,"column":1},"end":{"line":9,"column":1}},"key":"LybxBcWndh"},{"type":"text","value":", ","position":{"start":{"line":9,"column":1},"end":{"line":9,"column":1}},"key":"zqDZ4hqe17"},{"type":"inlineCode","value":"numpy","position":{"start":{"line":9,"column":1},"end":{"line":9,"column":1}},"key":"l7Ibt5TwUM"},{"type":"text","value":", ","position":{"start":{"line":9,"column":1},"end":{"line":9,"column":1}},"key":"YkbUyxjJS0"},{"type":"inlineCode","value":"matplotlib","position":{"start":{"line":9,"column":1},"end":{"line":9,"column":1}},"key":"ugd6fWVypc"},{"type":"text","value":", ","position":{"start":{"line":9,"column":1},"end":{"line":9,"column":1}},"key":"X0f6pmEd2b"},{"type":"inlineCode","value":"seaborn","position":{"start":{"line":9,"column":1},"end":{"line":9,"column":1}},"key":"rRjVjhEgen"}],"key":"QYgQ5ZLeWk"}],"key":"vCjtCw2vFl"},{"type":"tableRow","position":{"start":{"line":10,"column":1},"end":{"line":10,"column":1}},"children":[{"type":"tableCell","align":"left","position":{"start":{"line":10,"column":1},"end":{"line":10,"column":1}},"children":[{"type":"strong","position":{"start":{"line":10,"column":1},"end":{"line":10,"column":1}},"children":[{"type":"text","value":"Status:","position":{"start":{"line":10,"column":1},"end":{"line":10,"column":1}},"key":"P7Kp2uyYQ4"}],"key":"YxGU8OkWTe"}],"key":"HB0QoPsx2p"},{"type":"tableCell","align":"left","position":{"start":{"line":10,"column":1},"end":{"line":10,"column":1}},"children":[{"type":"text","value":"🟡 In Bearbeitung (Draft)","position":{"start":{"line":10,"column":1},"end":{"line":10,"column":1}},"key":"ikWHFfObcw"}],"key":"Q73m3dJOQO"}],"key":"s5MHpw6srT"}],"key":"WJZwtIRqCv"},{"type":"blockquote","position":{"start":{"line":12,"column":1},"end":{"line":12,"column":1}},"children":[{"type":"paragraph","position":{"start":{"line":12,"column":1},"end":{"line":12,"column":1}},"children":[{"type":"strong","position":{"start":{"line":12,"column":1},"end":{"line":12,"column":1}},"children":[{"type":"text","value":"Kontakt:","position":{"start":{"line":12,"column":1},"end":{"line":12,"column":1}},"key":"Z4w41Pwz69"}],"key":"zRUYmJweE6"},{"type":"text","value":" Bei Fragen oder Fehlern im Code öffne bitte ein Issue im Git-Repository oder schreibe eine kurze Nachricht im Team-Chat.","position":{"start":{"line":12,"column":1},"end":{"line":12,"column":1}},"key":"Vo5HE2ISiu"}],"key":"e5gzOVWXYW"}],"key":"u9WjTALDwx"}],"key":"NFAkKm7tBv"},{"type":"block","kind":"notebook-content","children":[{"type":"heading","depth":1,"position":{"start":{"line":1,"column":1},"end":{"line":1,"column":1}},"children":[{"type":"text","value":"🎨 Beispiel 6: Textformatierungen & Zitate (Cheat Sheet)","position":{"start":{"line":1,"column":1},"end":{"line":1,"column":1}},"key":"k3yKeTqJqB"}],"identifier":"id-beispiel-6-textformatierungen-zitate-cheat-sheet","label":"🎨 Beispiel 6: Textformatierungen & Zitate (Cheat Sheet)","html_id":"id-beispiel-6-textformatierungen-zitate-cheat-sheet","implicit":true,"key":"J7930IMceJ"},{"type":"paragraph","position":{"start":{"line":2,"column":1},"end":{"line":2,"column":1}},"children":[{"type":"text","value":"Ein kleiner Spickzettel, den du im Notebook lassen kannst, um schnell zu sehen, wie man Text hervorhebt.","position":{"start":{"line":2,"column":1},"end":{"line":2,"column":1}},"key":"SiILPO91HG"}],"key":"qEY3VOyls5"}],"key":"suHuhYekqP"},{"type":"block","kind":"notebook-content","children":[{"type":"heading","depth":2,"position":{"start":{"line":1,"column":1},"end":{"line":1,"column":1}},"children":[{"type":"text","value":"📝 Textformatierungs-Spickzettel","position":{"start":{"line":1,"column":1},"end":{"line":1,"column":1}},"key":"yWOh2MG5yE"}],"identifier":"id-textformatierungs-spickzettel","label":"📝 Textformatierungs-Spickzettel","html_id":"id-textformatierungs-spickzettel","implicit":true,"key":"mgATY1fwV0"},{"type":"paragraph","position":{"start":{"line":3,"column":1},"end":{"line":3,"column":1}},"children":[{"type":"text","value":"Du kannst Text auf verschiedene Arten hervorheben, um die Lesbarkeit zu verbessern:","position":{"start":{"line":3,"column":1},"end":{"line":3,"column":1}},"key":"n3xJ5N1wJz"}],"key":"GER6XNOkFb"},{"type":"list","ordered":false,"spread":false,"position":{"start":{"line":5,"column":1},"end":{"line":9,"column":1}},"children":[{"type":"listItem","spread":true,"position":{"start":{"line":5,"column":1},"end":{"line":5,"column":1}},"children":[{"type":"paragraph","children":[{"type":"text","value":"Das ist ","position":{"start":{"line":5,"column":1},"end":{"line":5,"column":1}},"key":"BcjZ8B3FDc"},{"type":"strong","position":{"start":{"line":5,"column":1},"end":{"line":5,"column":1}},"children":[{"type":"text","value":"fetter Text","position":{"start":{"line":5,"column":1},"end":{"line":5,"column":1}},"key":"bGNK5FYrGI"}],"key":"hmC39AY3V1"},{"type":"text","value":" für wichtige Begriffe.","position":{"start":{"line":5,"column":1},"end":{"line":5,"column":1}},"key":"qvf3Ek2YK2"}],"key":"j917Mkd0NX"}],"key":"ISEXFfQlmc"},{"type":"listItem","spread":true,"position":{"start":{"line":6,"column":1},"end":{"line":6,"column":1}},"children":[{"type":"paragraph","children":[{"type":"text","value":"Das ist ","position":{"start":{"line":6,"column":1},"end":{"line":6,"column":1}},"key":"PFq9hOKtGD"},{"type":"emphasis","position":{"start":{"line":6,"column":1},"end":{"line":6,"column":1}},"children":[{"type":"text","value":"kursiver Text","position":{"start":{"line":6,"column":1},"end":{"line":6,"column":1}},"key":"KGtf1AiRYr"}],"key":"v7tKGCTcNu"},{"type":"text","value":" für Betonungen.","position":{"start":{"line":6,"column":1},"end":{"line":6,"column":1}},"key":"RWl256gZyG"}],"key":"eY7PnQjR8c"}],"key":"bKhqXUyD3Y"},{"type":"listItem","spread":true,"position":{"start":{"line":7,"column":1},"end":{"line":7,"column":1}},"children":[{"type":"paragraph","children":[{"type":"text","value":"Du kannst Text auch ~~durchstreichen~~.","position":{"start":{"line":7,"column":1},"end":{"line":7,"column":1}},"key":"qpMmDYfarn"}],"key":"ungKRXmp1f"}],"key":"D2sWnQYLuL"},{"type":"listItem","spread":true,"position":{"start":{"line":8,"column":1},"end":{"line":9,"column":1}},"children":[{"type":"paragraph","children":[{"type":"text","value":"Für Code-Begriffe im Fließtext nutzt man Backticks: ","position":{"start":{"line":8,"column":1},"end":{"line":8,"column":1}},"key":"CUNvc1j7Q0"},{"type":"inlineCode","value":"Variable_X","position":{"start":{"line":8,"column":1},"end":{"line":8,"column":1}},"key":"PyftFa3Sag"},{"type":"text","value":".","position":{"start":{"line":8,"column":1},"end":{"line":8,"column":1}},"key":"OYcqjsT6yf"}],"key":"mCr0iIqa7J"}],"key":"qsV5rnowuj"}],"key":"WmwyLDDgAr"},{"type":"heading","depth":3,"position":{"start":{"line":10,"column":1},"end":{"line":10,"column":1}},"children":[{"type":"text","value":"Wichtige Zitate oder Definitionen:","position":{"start":{"line":10,"column":1},"end":{"line":10,"column":1}},"key":"DRj4fUFuFk"}],"identifier":"wichtige-zitate-oder-definitionen","label":"Wichtige Zitate oder Definitionen:","html_id":"wichtige-zitate-oder-definitionen","implicit":true,"key":"Si9idgAhTx"},{"type":"blockquote","position":{"start":{"line":12,"column":1},"end":{"line":13,"column":1}},"children":[{"type":"paragraph","position":{"start":{"line":12,"column":1},"end":{"line":13,"column":1}},"children":[{"type":"text","value":"“Ohne Daten bist du nur eine weitere Person mit einer Meinung.”\n— ","position":{"start":{"line":12,"column":1},"end":{"line":12,"column":1}},"key":"yLCXCDDY4v"},{"type":"emphasis","position":{"start":{"line":12,"column":1},"end":{"line":12,"column":1}},"children":[{"type":"text","value":"W. Edwards Deming","position":{"start":{"line":12,"column":1},"end":{"line":12,"column":1}},"key":"TiUjYBX1fT"}],"key":"odKOTMwKmU"}],"key":"YC1sd8GHnX"}],"key":"lIsnKVfhUc"},{"type":"paragraph","position":{"start":{"line":15,"column":1},"end":{"line":15,"column":1}},"children":[{"type":"text","value":"Wenn du einen horizontalen Trennstrich einfügen willst, tippe einfach drei Bindestriche ","position":{"start":{"line":15,"column":1},"end":{"line":15,"column":1}},"key":"JjbSh0FpUN"},{"type":"inlineCode","value":"---","position":{"start":{"line":15,"column":1},"end":{"line":15,"column":1}},"key":"ecksvrFihb"},{"type":"text","value":" in eine eigene Zeile (wie direkt hier drunter).","position":{"start":{"line":15,"column":1},"end":{"line":15,"column":1}},"key":"twK6qFSMo9"}],"key":"NBDksjMvKY"},{"type":"thematicBreak","position":{"start":{"line":17,"column":1},"end":{"line":17,"column":1}},"key":"hKNzWPzha7"}],"key":"sriKSeEIUJ"},{"type":"block","kind":"notebook-content","children":[{"type":"heading","depth":1,"position":{"start":{"line":1,"column":1},"end":{"line":1,"column":1}},"children":[{"type":"text","value":"🔥 Profi-Tipp für Jupyter Book:","position":{"start":{"line":1,"column":1},"end":{"line":1,"column":1}},"key":"XipdG2JO7h"}],"identifier":"id-profi-tipp-f-r-jupyter-book","label":"🔥 Profi-Tipp für Jupyter Book:","html_id":"id-profi-tipp-f-r-jupyter-book","implicit":true,"key":"iPnbVLT57W"},{"type":"paragraph","position":{"start":{"line":2,"column":1},"end":{"line":2,"column":1}},"children":[{"type":"text","value":"Wenn du Überschriften mit #, ## oder ### versiehst, erstellt Jupyter Book daraus beim Exportieren automatisch ein interaktives Inhaltsverzeichnis am rechten Bildrand der Website. Achte also darauf, deine Abschnitte gut zu strukturieren!","position":{"start":{"line":2,"column":1},"end":{"line":2,"column":1}},"key":"rk0ZPrup2P"}],"key":"lfYMiaHEwG"}],"key":"X94Z9aejGy"},{"type":"block","kind":"notebook-content","children":[{"type":"heading","depth":1,"position":{"start":{"line":1,"column":1},"end":{"line":1,"column":1}},"children":[{"type":"text","value":"🏗️ Beispiel 7: Technische Systemarchitektur & Ablauf (Text-basiert)","position":{"start":{"line":1,"column":1},"end":{"line":1,"column":1}},"key":"sLSrVPnw0N"}],"identifier":"id-beispiel-7-technische-systemarchitektur-ablauf-text-basiert","label":"🏗️ Beispiel 7: Technische Systemarchitektur & Ablauf (Text-basiert)","html_id":"id-beispiel-7-technische-systemarchitektur-ablauf-text-basiert","implicit":true,"key":"qc7QsPJam1"},{"type":"paragraph","position":{"start":{"line":2,"column":1},"end":{"line":2,"column":1}},"children":[{"type":"text","value":"Wenn du erklären möchtest, wie deine Daten durch das Skript fließen, ohne extra ein Bild zeichnen zu müssen.","position":{"start":{"line":2,"column":1},"end":{"line":2,"column":1}},"key":"ifHaDCB2wd"}],"key":"mKYBQnAxsl"}],"key":"UQ5MhmFs6C"},{"type":"block","kind":"notebook-content","children":[{"type":"heading","depth":2,"position":{"start":{"line":1,"column":1},"end":{"line":1,"column":1}},"children":[{"type":"text","value":"🔄 Daten-Pipeline und Workflow","position":{"start":{"line":1,"column":1},"end":{"line":1,"column":1}},"key":"lr9m82ilvE"}],"identifier":"id-daten-pipeline-und-workflow","label":"🔄 Daten-Pipeline und Workflow","html_id":"id-daten-pipeline-und-workflow","implicit":true,"key":"TgKrJVD7sz"},{"type":"paragraph","position":{"start":{"line":3,"column":1},"end":{"line":3,"column":1}},"children":[{"type":"text","value":"Bevor der Algorithmus trainiert werden kann, durchlaufen die Rohdaten eine mehrstufige Pipeline. Der Prozess ist wie folgt aufgebaut:","position":{"start":{"line":3,"column":1},"end":{"line":3,"column":1}},"key":"uVKsZC0gEO"}],"key":"QjMyyHcVDW"},{"type":"list","ordered":true,"start":1,"spread":false,"position":{"start":{"line":5,"column":1},"end":{"line":12,"column":1}},"children":[{"type":"listItem","spread":true,"position":{"start":{"line":5,"column":1},"end":{"line":6,"column":1}},"children":[{"type":"paragraph","children":[{"type":"strong","position":{"start":{"line":5,"column":1},"end":{"line":5,"column":1}},"children":[{"type":"text","value":"Datenbeschaffung (Ingestion)","position":{"start":{"line":5,"column":1},"end":{"line":5,"column":1}},"key":"oJR2nAsGP6"}],"key":"HdpXLy22Xd"}],"key":"TSEwQECoUj"},{"type":"list","ordered":false,"spread":false,"position":{"start":{"line":6,"column":1},"end":{"line":6,"column":1}},"children":[{"type":"listItem","spread":true,"position":{"start":{"line":6,"column":1},"end":{"line":6,"column":1}},"children":[{"type":"paragraph","children":[{"type":"text","value":"Import aus der SQL-Datenbank oder lokalen ","position":{"start":{"line":6,"column":1},"end":{"line":6,"column":1}},"key":"nwST6bhpuX"},{"type":"inlineCode","value":".csv","position":{"start":{"line":6,"column":1},"end":{"line":6,"column":1}},"key":"wKjA26mgFU"},{"type":"text","value":"-Dateien.","position":{"start":{"line":6,"column":1},"end":{"line":6,"column":1}},"key":"iMe0BdKIEw"}],"key":"iArP2V3Y71"}],"key":"CmmrdEV7kL"}],"key":"DayZKAiknI"}],"key":"xyamSJnsBM"},{"type":"listItem","spread":true,"position":{"start":{"line":7,"column":1},"end":{"line":9,"column":1}},"children":[{"type":"paragraph","children":[{"type":"strong","position":{"start":{"line":7,"column":1},"end":{"line":7,"column":1}},"children":[{"type":"text","value":"Bereinigung (Preprocessing)","position":{"start":{"line":7,"column":1},"end":{"line":7,"column":1}},"key":"UYOliL4YcI"}],"key":"fnKd6TVhyc"}],"key":"pFilvZhCcX"},{"type":"list","ordered":false,"spread":false,"position":{"start":{"line":8,"column":1},"end":{"line":9,"column":1}},"children":[{"type":"listItem","spread":true,"position":{"start":{"line":8,"column":1},"end":{"line":8,"column":1}},"children":[{"type":"paragraph","children":[{"type":"text","value":"Entfernung von Duplikaten.","position":{"start":{"line":8,"column":1},"end":{"line":8,"column":1}},"key":"fe3mj8oJ0E"}],"key":"YQq3ux6SMJ"}],"key":"t6dbp9jRDP"},{"type":"listItem","spread":true,"position":{"start":{"line":9,"column":1},"end":{"line":9,"column":1}},"children":[{"type":"paragraph","children":[{"type":"text","value":"Imputation fehlender Werte (z. B. Ersetzen von ","position":{"start":{"line":9,"column":1},"end":{"line":9,"column":1}},"key":"Sv39sW6XBs"},{"type":"inlineCode","value":"NaN","position":{"start":{"line":9,"column":1},"end":{"line":9,"column":1}},"key":"HQlf3a468j"},{"type":"text","value":" durch den Median).","position":{"start":{"line":9,"column":1},"end":{"line":9,"column":1}},"key":"F2TBgh9TZw"}],"key":"jSDo7HuXms"}],"key":"dkVbFAzovR"}],"key":"EZUGdkUhse"}],"key":"X6LUQxh7Ud"},{"type":"listItem","spread":true,"position":{"start":{"line":10,"column":1},"end":{"line":12,"column":1}},"children":[{"type":"paragraph","children":[{"type":"strong","position":{"start":{"line":10,"column":1},"end":{"line":10,"column":1}},"children":[{"type":"text","value":"Transformation (Feature Engineering)","position":{"start":{"line":10,"column":1},"end":{"line":10,"column":1}},"key":"KIuVFWPlPt"}],"key":"nSI0vxkyZ1"}],"key":"SdMakaO0A8"},{"type":"list","ordered":false,"spread":false,"position":{"start":{"line":11,"column":1},"end":{"line":12,"column":1}},"children":[{"type":"listItem","spread":true,"position":{"start":{"line":11,"column":1},"end":{"line":11,"column":1}},"children":[{"type":"paragraph","children":[{"type":"text","value":"Normalisierung numerischer Variablen.","position":{"start":{"line":11,"column":1},"end":{"line":11,"column":1}},"key":"sy5ef2dIAz"}],"key":"mp31451fng"}],"key":"eBpvQ8lqrY"},{"type":"listItem","spread":true,"position":{"start":{"line":12,"column":1},"end":{"line":12,"column":1}},"children":[{"type":"paragraph","children":[{"type":"text","value":"One-Hot-Encoding für kategoriale Features.","position":{"start":{"line":12,"column":1},"end":{"line":12,"column":1}},"key":"RhjVdYtrqJ"}],"key":"Ax0BKi0nco"}],"key":"rIqYk93wMZ"}],"key":"D6nJHB7h6y"}],"key":"radruK7Fya"}],"key":"PPkPmjmK5c"}],"key":"GQiKPU6A9w"},{"type":"block","kind":"notebook-content","children":[{"type":"paragraph","position":{"start":{"line":1,"column":1},"end":{"line":1,"column":1}},"children":[{"type":"text","value":"[Rohdaten] ──> (Bereinigung) ──> (Transformation) ──> [Bereite Daten für ML-Modell]","position":{"start":{"line":1,"column":1},"end":{"line":1,"column":1}},"key":"Yvcel4amMw"}],"key":"jrhCUI9abe"}],"key":"X40mId44a9"},{"type":"block","kind":"notebook-content","children":[{"type":"blockquote","position":{"start":{"line":1,"column":1},"end":{"line":1,"column":1}},"children":[{"type":"paragraph","position":{"start":{"line":1,"column":1},"end":{"line":1,"column":1}},"children":[{"type":"text","value":"ℹ️ ","position":{"start":{"line":1,"column":1},"end":{"line":1,"column":1}},"key":"G57GkrO62i"},{"type":"emphasis","position":{"start":{"line":1,"column":1},"end":{"line":1,"column":1}},"children":[{"type":"text","value":"Hinweis:","position":{"start":{"line":1,"column":1},"end":{"line":1,"column":1}},"key":"rCu4wyuYga"}],"key":"SnTMLmbD3r"},{"type":"text","value":" Jede dieser Stufen ist im Notebook in einer eigenen Sektion (","position":{"start":{"line":1,"column":1},"end":{"line":1,"column":1}},"key":"Qdq55dtLjZ"},{"type":"inlineCode","value":"##","position":{"start":{"line":1,"column":1},"end":{"line":1,"column":1}},"key":"FOIIv6pxaD"},{"type":"text","value":") gekapselt, um den Code modular zu halten.","position":{"start":{"line":1,"column":1},"end":{"line":1,"column":1}},"key":"y3seHyTFsp"}],"key":"X2th2amwQR"}],"key":"yFd79gPD8z"}],"key":"OU9AnlsMGg"},{"type":"block","kind":"notebook-content","children":[{"type":"heading","depth":1,"position":{"start":{"line":1,"column":1},"end":{"line":1,"column":1}},"children":[{"type":"text","value":"🎨 Beispiel 8: HTML-Erweiterungen (Farbige Texte und Zentrierung)","position":{"start":{"line":1,"column":1},"end":{"line":1,"column":1}},"key":"uvpgFVahjb"}],"identifier":"id-beispiel-8-html-erweiterungen-farbige-texte-und-zentrierung","label":"🎨 Beispiel 8: HTML-Erweiterungen (Farbige Texte und Zentrierung)","html_id":"id-beispiel-8-html-erweiterungen-farbige-texte-und-zentrierung","implicit":true,"key":"wBe5DYArhA"},{"type":"paragraph","position":{"start":{"line":2,"column":1},"end":{"line":2,"column":1}},"children":[{"type":"text","value":"Standard-Markdown ist manchmal gestalterisch limitiert. Da Jupyter Notebooks HTML unterstützen, kannst du das Design direkt im Markdown-Code anpassen:","position":{"start":{"line":2,"column":1},"end":{"line":2,"column":1}},"key":"vb2e0d9U7V"}],"key":"SfjAncTeDV"}],"key":"LQi0I3DP6q"},{"type":"block","kind":"notebook-content","children":[{"type":"heading","depth":2,"position":{"start":{"line":1,"column":1},"end":{"line":1,"column":1}},"children":[{"type":"text","value":"🌟 Wichtige Projektankündigung","position":{"start":{"line":1,"column":1},"end":{"line":1,"column":1}},"key":"R5Nvu57C7W"}],"identifier":"id-wichtige-projektank-ndigung","label":"🌟 Wichtige Projektankündigung","html_id":"id-wichtige-projektank-ndigung","implicit":true,"key":"p3FhFNvc00"},{"type":"paragraph","position":{"start":{"line":3,"column":1},"end":{"line":3,"column":1}},"children":[{"type":"text","value":"Manchmal reicht fetter Text nicht aus. Hier sind ein paar HTML-Kniffe für dein Notebook:","position":{"start":{"line":3,"column":1},"end":{"line":3,"column":1}},"key":"qtjYQduCu2"}],"key":"lc8nIsG7Dc"},{"type":"paragraph","children":[{"type":"strong","children":[{"type":"text","value":"💡 Wichtiger Meilenstein:","key":"U5dQVCaCW9"}],"key":"sH0Z8QquuG"},{"type":"text","value":" Die Datenbasis wurde erfolgreich validiert. Alle nachfolgenden Analysen basieren auf dem verifizierten Datensatz vom Q2.","key":"xl241Jg1aL"}],"key":"ONePiT2geY"},{"type":"heading","depth":3,"position":{"start":{"line":10,"column":1},"end":{"line":10,"column":1}},"children":[{"type":"text","value":"Farbliche Hervorhebungen im Fließtext:","position":{"start":{"line":10,"column":1},"end":{"line":10,"column":1}},"key":"Q7KHxOsKWD"}],"identifier":"farbliche-hervorhebungen-im-flie-text","label":"Farbliche Hervorhebungen im Fließtext:","html_id":"farbliche-hervorhebungen-im-flie-text","implicit":true,"key":"O0PYUzddJ0"},{"type":"list","ordered":false,"spread":false,"position":{"start":{"line":12,"column":1},"end":{"line":14,"column":1}},"children":[{"type":"listItem","spread":true,"position":{"start":{"line":12,"column":1},"end":{"line":12,"column":1}},"children":[{"type":"paragraph","children":[{"type":"text","value":"Um ein Problem anzuzeigen: ","position":{"start":{"line":12,"column":1},"end":{"line":12,"column":1}},"key":"yXAMMGuXU5"},{"type":"span","style":{"color":"#d32f2f","fontWeight":"bold"},"children":[{"type":"text","value":"Kritischer Fehler im Import-Skript","key":"InXvezG1nu"}],"key":"eb82iy8frl"},{"type":"text","value":" (siehe Zelle 12).","position":{"start":{"line":12,"column":1},"end":{"line":12,"column":1}},"key":"XPQsTK6Oke"}],"key":"huw6mYSjgW"}],"key":"bM896DnM17"},{"type":"listItem","spread":true,"position":{"start":{"line":13,"column":1},"end":{"line":13,"column":1}},"children":[{"type":"paragraph","children":[{"type":"text","value":"Um Erfolg anzuzeigen: ","position":{"start":{"line":13,"column":1},"end":{"line":13,"column":1}},"key":"Do5zmRKxj0"},{"type":"span","style":{"color":"#388e3c","fontWeight":"bold"},"children":[{"type":"text","value":"Modell-Genauigkeit liegt bei über 92%","key":"MggDxUb2ge"}],"key":"Mhiimqfl2F"},{"type":"text","value":".","position":{"start":{"line":13,"column":1},"end":{"line":13,"column":1}},"key":"FvJNadKYQ5"}],"key":"I6Iqf1nMoF"}],"key":"daBDQ7dmlg"},{"type":"listItem","spread":true,"position":{"start":{"line":14,"column":1},"end":{"line":14,"column":1}},"children":[{"type":"paragraph","children":[{"type":"text","value":"Um eine Warnung anzuzeigen: ","position":{"start":{"line":14,"column":1},"end":{"line":14,"column":1}},"key":"KYkmSAYiXW"},{"type":"span","style":{"color":"#f57c00","fontWeight":"bold"},"children":[{"type":"text","value":"Laufzeit beachten!","key":"gOcK6yKGT7"}],"key":"vXtr6bmeXt"},{"type":"text","value":" Große Schleifen können mehrere Minuten dauern.","position":{"start":{"line":14,"column":1},"end":{"line":14,"column":1}},"key":"B6QLqN4r7M"}],"key":"Koes2pbPkC"}],"key":"dG00ensGRm"}],"key":"cb3yVV14Sx"}],"key":"kMcKRQpgiX"},{"type":"block","kind":"notebook-content","children":[{"type":"heading","depth":1,"position":{"start":{"line":1,"column":1},"end":{"line":1,"column":1}},"children":[{"type":"text","value":"📘 Beispiel 9: Spezielle Jupyter Book Panels (Zweispaltiges Layout)","position":{"start":{"line":1,"column":1},"end":{"line":1,"column":1}},"key":"Mg8xS3fMD8"}],"identifier":"id-beispiel-9-spezielle-jupyter-book-panels-zweispaltiges-layout","label":"📘 Beispiel 9: Spezielle Jupyter Book Panels (Zweispaltiges Layout)","html_id":"id-beispiel-9-spezielle-jupyter-book-panels-zweispaltiges-layout","implicit":true,"key":"nxLU2AfE2v"},{"type":"paragraph","position":{"start":{"line":2,"column":1},"end":{"line":2,"column":1}},"children":[{"type":"text","value":"Wenn du dein Notebook mit Jupyter Book baust, kannst du Inhalte über spezielle Direktiven nebeneinander anordnen (Sidebars oder Panels). Das bricht die starre “Top-to-Bottom”-Struktur auf.","position":{"start":{"line":2,"column":1},"end":{"line":2,"column":1}},"key":"zoxS7a1P1x"}],"key":"wuony6wbhY"}],"key":"vOmnwXPqBz"},{"type":"block","kind":"notebook-content","children":[{"type":"heading","depth":2,"position":{"start":{"line":1,"column":1},"end":{"line":1,"column":1}},"children":[{"type":"text","value":"📈 Analyse der Performance","position":{"start":{"line":1,"column":1},"end":{"line":1,"column":1}},"key":"Cqijnpviqy"}],"identifier":"id-analyse-der-performance","label":"📈 Analyse der Performance","html_id":"id-analyse-der-performance","implicit":true,"key":"XXyDFw67a2"},{"type":"paragraph","position":{"start":{"line":3,"column":1},"end":{"line":3,"column":1}},"children":[{"type":"text","value":"Hier werten wir die Geschwindigkeit unserer Abfragen aus. Während der Hauptcode die Berechnungen anstellt, kannst du rechts oder in einer separaten Box die Hardware-Voraussetzungen einsehen.","position":{"start":{"line":3,"column":1},"end":{"line":3,"column":1}},"key":"CNsCHl9NNS"}],"key":"KZVEl6JtCu"},{"type":"aside","kind":"sidebar","children":[{"type":"admonitionTitle","children":[{"type":"text","value":"Hardware-Spezifikationen","position":{"start":{"line":5,"column":1},"end":{"line":5,"column":1}},"key":"RU56X77abO"}],"key":"UVUnN0HeM7"},{"type":"list","ordered":false,"spread":false,"position":{"start":{"line":6,"column":1},"end":{"line":9,"column":1}},"children":[{"type":"listItem","spread":true,"position":{"start":{"line":6,"column":1},"end":{"line":6,"column":1}},"children":[{"type":"paragraph","children":[{"type":"strong","position":{"start":{"line":6,"column":1},"end":{"line":6,"column":1}},"children":[{"type":"text","value":"CPU:","position":{"start":{"line":6,"column":1},"end":{"line":6,"column":1}},"key":"NYfFlwVAwp"}],"key":"FUvaqk1Nek"},{"type":"text","value":" 8 Cores (vCPU)","position":{"start":{"line":6,"column":1},"end":{"line":6,"column":1}},"key":"LA3G7iWWE5"}],"key":"BLF0fEez4G"}],"key":"yDhwgioyNK"},{"type":"listItem","spread":true,"position":{"start":{"line":7,"column":1},"end":{"line":7,"column":1}},"children":[{"type":"paragraph","children":[{"type":"strong","position":{"start":{"line":7,"column":1},"end":{"line":7,"column":1}},"children":[{"type":"text","value":"RAM:","position":{"start":{"line":7,"column":1},"end":{"line":7,"column":1}},"key":"TVzB8tfKa3"}],"key":"KP3pYcBInE"},{"type":"text","value":" 16 GB","position":{"start":{"line":7,"column":1},"end":{"line":7,"column":1}},"key":"eXqdFGk1Vs"}],"key":"z19sMJmBfY"}],"key":"Tx1kCPIgEa"},{"type":"listItem","spread":true,"position":{"start":{"line":8,"column":1},"end":{"line":8,"column":1}},"children":[{"type":"paragraph","children":[{"type":"strong","position":{"start":{"line":8,"column":1},"end":{"line":8,"column":1}},"children":[{"type":"text","value":"Laufzeit:","position":{"start":{"line":8,"column":1},"end":{"line":8,"column":1}},"key":"Z8p1kAlM2Z"}],"key":"wj1tIpBTAn"},{"type":"text","value":" ~14.2 Sekunden","position":{"start":{"line":8,"column":1},"end":{"line":8,"column":1}},"key":"sSHi7qUuBg"}],"key":"pVMTc3mDwI"}],"key":"scyWfCHB7b"},{"type":"listItem","spread":true,"position":{"start":{"line":9,"column":1},"end":{"line":9,"column":1}},"children":[{"type":"paragraph","children":[{"type":"strong","position":{"start":{"line":9,"column":1},"end":{"line":9,"column":1}},"children":[{"type":"text","value":"Bibliothek:","position":{"start":{"line":9,"column":1},"end":{"line":9,"column":1}},"key":"d6wOloTXWH"}],"key":"Z1n7iMI8Du"},{"type":"text","value":" ","position":{"start":{"line":9,"column":1},"end":{"line":9,"column":1}},"key":"TScUlouSf5"},{"type":"inlineCode","value":"pandas","position":{"start":{"line":9,"column":1},"end":{"line":9,"column":1}},"key":"HMraqNdkF5"},{"type":"text","value":" v2.x","position":{"start":{"line":9,"column":1},"end":{"line":9,"column":1}},"key":"Bsr9d1BHRW"}],"key":"TaiK4W10kO"}],"key":"K3et43KfFn"}],"key":"TZqsYJIVG3"}],"key":"dMZLgPj0L9"}],"key":"qzAkR1M7gK"},{"type":"block","kind":"notebook-content","children":[{"type":"paragraph","position":{"start":{"line":1,"column":1},"end":{"line":1,"column":1}},"children":[{"type":"text","value":"Wir sehen deutlich, dass die RAM-Auslastung stabil bleibt, da wir die Daten gestreamt und nicht komplett in den Speicher geladen haben.","position":{"start":{"line":1,"column":1},"end":{"line":1,"column":1}},"key":"RE0plsKKu2"}],"key":"Z9eTRh7ZZr"}],"key":"VfmfM1l4CM"},{"type":"block","kind":"notebook-content","children":[{"type":"paragraph","position":{"start":{"line":1,"column":1},"end":{"line":1,"column":1}},"children":[{"type":"text","value":"Auswertung der Metriken:","position":{"start":{"line":1,"column":1},"end":{"line":1,"column":1}},"key":"htoLxbLlCw"}],"key":"wjeNdTv10b"},{"type":"paragraph","position":{"start":{"line":3,"column":1},"end":{"line":3,"column":1}},"children":[{"type":"text","value":"Latenz: Minimiert durch Indexierung.","position":{"start":{"line":3,"column":1},"end":{"line":3,"column":1}},"key":"u0P4p1QoBg"}],"key":"Q1RdR62Uwb"},{"type":"paragraph","position":{"start":{"line":5,"column":1},"end":{"line":5,"column":1}},"children":[{"type":"text","value":"Durchsatz: 5000 Zeilen/Sekunde.","position":{"start":{"line":5,"column":1},"end":{"line":5,"column":1}},"key":"oh5QfSM3TF"}],"key":"HyPqi43zRc"}],"key":"t36qM44G4N"},{"type":"block","kind":"notebook-content","children":[{"type":"thematicBreak","position":{"start":{"line":1,"column":1},"end":{"line":1,"column":1}},"key":"C0PCekWzkN"},{"type":"heading","depth":2,"position":{"start":{"line":3,"column":1},"end":{"line":3,"column":1}},"children":[{"type":"text","value":"💡 Ein kleiner Trick:","position":{"start":{"line":3,"column":1},"end":{"line":3,"column":1}},"key":"kPvwuUeO2s"}],"identifier":"id-ein-kleiner-trick","label":"💡 Ein kleiner Trick:","html_id":"id-ein-kleiner-trick","implicit":true,"key":"yhVdek4yBO"},{"type":"paragraph","position":{"start":{"line":4,"column":1},"end":{"line":4,"column":1}},"children":[{"type":"text","value":"Wenn du in einer Markdown-Zelle schnell Code-Stücke schreiben willst, ohne dass Python sie ausführt, nutze einfach die dreifachen Backticks ","position":{"start":{"line":4,"column":1},"end":{"line":4,"column":1}},"key":"YTncqzr4bh"},{"type":"inlineCode","value":"```python","position":{"start":{"line":4,"column":1},"end":{"line":4,"column":1}},"key":"dZqi5fV4i2"},{"type":"text","value":" am Anfang und ","position":{"start":{"line":4,"column":1},"end":{"line":4,"column":1}},"key":"xRjTBOvOYD"},{"type":"inlineCode","value":"```","position":{"start":{"line":4,"column":1},"end":{"line":4,"column":1}},"key":"gETKc1kALO"},{"type":"text","value":" am Ende, so wie in diesen Beispielen. Jupyter rendert das dann als formatierten Text mit Syntax-Highlighting!","position":{"start":{"line":4,"column":1},"end":{"line":4,"column":1}},"key":"FcqSqWmojD"}],"key":"toga8Hh9Rw"}],"key":"uw7Xu4HBwc"}],"key":"z6CBlLehIU"},"references":{"cite":{"order":[],"data":{}}}}